{
    "GNN_DATA": {
        "edges": [
            {
                "dst": "4469532_0",
                "src": "4469498_root"
            },
            {
                "dst": "4469532_1",
                "src": "4469498_root"
            },
            {
                "dst": "4469542_0",
                "src": "4469532_0"
            },
            {
                "dst": "loopSeerDum",
                "src": "4469542_0"
            },
            {
                "dst": "4469537_1",
                "src": "4469532_1"
            },
            {
                "dst": "4469542_1",
                "src": "4469537_1"
            },
            {
                "dst": "loopSeerDum",
                "src": "4469542_1"
            }
        ],
        "nodes": [
            {
                "block_addr": 4469498,
                "constraints": [
                    [
                        0,
                        []
                    ]
                ],
                "instructions": "push|rbp|    |mov|rbp|rsp|    |sub|rsp|0x10|    |mov|qword|ptr|rbp|-|8|rdi|    |mov|rax|qword|ptr|rip|+|0x23114b|    |mov|rdx|qword|ptr|rbp|-|8|    |mov|rsi|rdx|    |mov|rdi|rax|    |call|0x44a6ff|    ",
                "key": "4469498_root",
                "path_num": -1
            },
            {
                "block_addr": 4469532,
                "constraints": [
                    [
                        1,
                        []
                    ]
                ],
                "instructions": "test|rax|rax|    |jne|0x443326|    ",
                "key": "4469532_0",
                "path_num": 0
            },
            {
                "block_addr": 4469542,
                "constraints": [
                    [
                        2,
                        [
                            "<Bool __ne__(fake_ret_value_717_64, 0x0)>"
                        ]
                    ]
                ],
                "instructions": "nop|    |leave|    |ret|    ",
                "key": "4469542_0",
                "path_num": 0
            },
            {
                "block_addr": "loopSeerDum",
                "constraints": [
                    [
                        3,
                        [
                            "<BV32 Extract(31, 0, fake_ret_value_717_64)>"
                        ]
                    ],
                    [
                        4,
                        [
                            "<BV32 Extract(31, 0, fake_ret_value_718_64)>"
                        ]
                    ]
                ],
                "instructions": "no_instructions",
                "key": "loopSeerDum",
                "path_num": 0
            },
            {
                "block_addr": 4469532,
                "constraints": [
                    [
                        1,
                        []
                    ]
                ],
                "instructions": "test|rax|rax|    |jne|0x443326|    ",
                "key": "4469532_1",
                "path_num": 1
            },
            {
                "block_addr": 4469537,
                "constraints": [
                    [
                        2,
                        [
                            "<Bool __eq__(fake_ret_value_717_64, 0x0)>"
                        ]
                    ]
                ],
                "instructions": "call|0x44dd45|    ",
                "key": "4469537_1",
                "path_num": 1
            },
            {
                "block_addr": 4469542,
                "constraints": [
                    [
                        3,
                        []
                    ]
                ],
                "instructions": "nop|    |leave|    |ret|    ",
                "key": "4469542_1",
                "path_num": 1
            }
        ]
    },
    "func_name": "state_hash_insert"
}